matchmaker/wsgi.py
matchmaker/application/NextRoundMatchesTypes.py
matchmaker/application/QueryContext.py
matchmaker/application/__init__.py
matchmaker/application/matchmaker.py
matchmaker/application/routes.py
matchmaker_t4-0.2.0.dist-info/METADATA
matchmaker_t4-0.2.0.dist-info/WHEEL
matchmaker_t4-0.2.0.dist-info/top_level.txt
matchmaker_t4-0.2.0.dist-info/RECORD
