Metadata-Version: 2.1
Name: matchmaker-t4
Version: 0.2.0
Summary: Matchmaker service for tabletoptournament.tools
Author-email: Cory Benson <ardaedhel@gmail.com>
Project-URL: Homepage, https://github.com/sprintska/t4_matchmaker
Classifier: Programming Language :: Python :: 3
Classifier: License :: OSI Approved :: GNU General Public License v3 or later (GPLv3+)
Classifier: Operating System :: POSIX :: Linux
Requires-Python: >=3.8
Requires-Dist: flask
Requires-Dist: requests
Requires-Dist: gunicorn
